README.rst
setup.cfg
setup.py
peek_doc_user/__init__.py
peek_doc_user/build_html_docs.sh
peek_doc_user/build_latex_docs.sh
peek_doc_user/conf.py
peek_doc_user/index.rst
peek_doc_user/watch_docs.sh
peek_doc_user/welcome.rst
peek_doc_user.egg-info/PKG-INFO
peek_doc_user.egg-info/SOURCES.txt
peek_doc_user.egg-info/dependency_links.txt
peek_doc_user.egg-info/not-zip-safe
peek_doc_user.egg-info/requires.txt
peek_doc_user.egg-info/top_level.txt
peek_doc_user/_static/.gitkeep
peek_doc_user/_static/fonts/fontawesome-webfont.woff2